[
  {
    "command": "?",
    "description": "Show available commands."
  },
  {
    "command": "help",
    "description": "Show available commands."
  },
  {
    "command": "home",
    "description": "Switch to the homepage tab."
  },
  {
    "command": "about",
    "description": "Switch to the profile and background tab."
  },
  {
    "command": "projects",
    "description": "Switch to selected projects and portfolio work."
  },
  {
    "command": "research",
    "description": "Switch to research interests and statement."
  },
  {
    "command": "models",
    "description": "Switch to the model playground tab."
  },
  {
    "command": "notes",
    "description": "Switch to the digital garden notes tab."
  },
  {
    "command": "teaching",
    "description": "Switch to teaching and educational resources."
  },
  {
    "command": "cv",
    "description": "Switch to public-safe CV information."
  },
  {
    "command": "contact",
    "description": "Switch to public contact channels."
  },
  {
    "command": "clear",
    "description": "Clear the terminal output."
  },
  {
    "command": "model toggle",
    "description": "Activate the GFP/RFP-like toggle lattice backup."
  },
  {
    "command": "model flock",
    "description": "Activate the three-population Vicsek flock field."
  },
  {
    "command": "model quorum",
    "description": "Activate the quorum-sensing model placeholder."
  },
  {
    "command": "perturb",
    "description": "Perturb the active simulation."
  },
  {
    "command": "reset",
    "description": "Reset the active simulation."
  }
]
